<?xml version="1.0" encoding='UTF-8'?>
<!DOCTYPE hibernate-mapping PUBLIC
                            "-//Hibernate/Hibernate Mapping DTD 3.0//EN"
                            "http://hibernate.sourceforge.net/hibernate-mapping-3.0.dtd" >


<hibernate-mapping>

	<class name="org.mifos.customers.business.CustomerActivityEntity" table="customer_account_activity">
		<id name="customerActivityId" column="customer_account_activity_id" type="integer" access="field">
			<generator class="native" />
		</id>
		<property name="amount" type="org.mifos.framework.util.helpers.MoneyCompositeUserType" access="field">
			<column name="fee_amount_currency_id" />
			<column name="amount" />
		</property>
		<property name="description" column="description" access="field" />
		<property name="createdDate" column="created_date" access="field" />
		<many-to-one name="customerAccount" column="account_id" class="org.mifos.customers.business.CustomerAccountBO" access="field" />
		<many-to-one name="personnel" column="created_by" class="org.mifos.customers.personnel.business.PersonnelBO" cascade="none" update="false" insert="true" unique="true" access="field" />
	</class>
</hibernate-mapping>
